anemoi/models/__init__.py
anemoi/models/__main__.py
anemoi/models/_version.py
anemoi/models/commands/__init__.py
anemoi/models/commands/hello.py
anemoi/models/commands/migration.py
anemoi/models/data_indices/__init__.py
anemoi/models/data_indices/collection.py
anemoi/models/data_indices/index.py
anemoi/models/data_indices/tensor.py
anemoi/models/distributed/__init__.py
anemoi/models/distributed/balanced_partition.py
anemoi/models/distributed/graph.py
anemoi/models/distributed/khop_edges.py
anemoi/models/distributed/primitives.py
anemoi/models/distributed/shapes.py
anemoi/models/distributed/transformer.py
anemoi/models/distributed/utils.py
anemoi/models/interface/__init__.py
anemoi/models/layers/__init__.py
anemoi/models/layers/activations.py
anemoi/models/layers/attention.py
anemoi/models/layers/block.py
anemoi/models/layers/bounding.py
anemoi/models/layers/conv.py
anemoi/models/layers/diffusion.py
anemoi/models/layers/ensemble.py
anemoi/models/layers/graph.py
anemoi/models/layers/graph_provider.py
anemoi/models/layers/mapper.py
anemoi/models/layers/mlp.py
anemoi/models/layers/normalization.py
anemoi/models/layers/processor.py
anemoi/models/layers/residual.py
anemoi/models/layers/sparse_projector.py
anemoi/models/layers/spectral_transforms.py
anemoi/models/layers/utils.py
anemoi/models/migrations/__init__.py
anemoi/models/migrations/migrator.py
anemoi/models/migrations/setup_context.py
anemoi/models/migrations/scripts/1755530253_initial.py
anemoi/models/migrations/scripts/1762857427_deprecate_eda.py
anemoi/models/migrations/scripts/1762857428_chunking_fix.py
anemoi/models/migrations/scripts/1763479917_hardware_schema_update.py
anemoi/models/migrations/scripts/1763479918_refactor_mapper.py
anemoi/models/models/__init__.py
anemoi/models/models/base.py
anemoi/models/models/diffusion_encoder_processor_decoder.py
anemoi/models/models/encoder_processor_decoder.py
anemoi/models/models/ens_encoder_processor_decoder.py
anemoi/models/models/hierarchical.py
anemoi_models-0.11.3.dist-info/licenses/LICENSE
anemoi_models-0.11.3.dist-info/METADATA
anemoi_models-0.11.3.dist-info/WHEEL
anemoi_models-0.11.3.dist-info/entry_points.txt
anemoi_models-0.11.3.dist-info/top_level.txt
anemoi_models-0.11.3.dist-info/RECORD
