Metadata-Version: 2.4
Name: anemoi-models
Version: 0.11.3
Summary: A package to hold various functions to support training of ML models.
Author-email: "European Centre for Medium-Range Weather Forecasts (ECMWF)" <software.support@ecmwf.int>
License:                                  Apache License
Project-URL: Documentation, https://anemoi-models.readthedocs.io/
Project-URL: Homepage, https://github.com/ecmwf/anemoi-models/
Project-URL: Issues, https://github.com/ecmwf/anemoi-models/issues
Project-URL: Repository, https://github.com/ecmwf/anemoi-models/
Keywords: ai,models,tools
Classifier: Development Status :: 4 - Beta
Classifier: Intended Audience :: Developers
Classifier: License :: OSI Approved :: Apache Software License
Classifier: Operating System :: OS Independent
Classifier: Programming Language :: Python :: 3 :: Only
Classifier: Programming Language :: Python :: 3.10
Classifier: Programming Language :: Python :: 3.11
Classifier: Programming Language :: Python :: 3.12
Classifier: Programming Language :: Python :: Implementation :: CPython
Classifier: Programming Language :: Python :: Implementation :: PyPy
Requires-Python: >=3.10
License-File: LICENSE
Requires-Dist: anemoi-utils>=0.1.9
Requires-Dist: einops>=0.6.1
Requires-Dist: hydra-core>=1.3
Requires-Dist: torch>=2.3
Requires-Dist: torch-geometric>=2.3
Provides-Extra: all
Requires-Dist: anemoi-models[migrations]; extra == "all"
Provides-Extra: dev
Requires-Dist: anemoi-models[all,docs,tests]; extra == "dev"
Requires-Dist: pre-commit>=3.3.3; extra == "dev"
Provides-Extra: docs
Requires-Dist: nbsphinx; extra == "docs"
Requires-Dist: pandoc; extra == "docs"
Requires-Dist: rstfmt; extra == "docs"
Requires-Dist: sphinx<8.2; python_version < "3.11" and extra == "docs"
Requires-Dist: sphinx>=8.2; python_version >= "3.11" and extra == "docs"
Requires-Dist: sphinx-argparse<0.5; extra == "docs"
Requires-Dist: sphinx-rtd-theme; extra == "docs"
Provides-Extra: migrations
Requires-Dist: cloudpickle>=3.1; extra == "migrations"
Requires-Dist: jinja2>=3.1; extra == "migrations"
Requires-Dist: rich; extra == "migrations"
Provides-Extra: tests
Requires-Dist: hypothesis>=6.11; extra == "tests"
Requires-Dist: pytest>=8; extra == "tests"
Dynamic: license-file
